AUTHORS.rst
CONTRIBUTING.rst
HISTORY.rst
LICENSE
MANIFEST.in
README.rst
requirements.txt
setup.cfg
setup.py
BioCompass/BioCompass.py
BioCompass/__init__.py
BioCompass/category_gen.py
BioCompass/cli.py
BioCompass/edges_gen.py
BioCompass/feature_gen.py
BioCompass/filter_edges.py
BioCompass/keep_best_itineration.py
BioCompass/subcluster_dictionary.json
BioCompass/subcluster_gen.py
BioCompass/table_1_extender.py
BioCompass/table_1_gen.py
BioCompass.egg-info/PKG-INFO
BioCompass.egg-info/SOURCES.txt
BioCompass.egg-info/dependency_links.txt
BioCompass.egg-info/entry_points.txt
BioCompass.egg-info/not-zip-safe
BioCompass.egg-info/requires.txt
BioCompass.egg-info/top_level.txt
docs/Makefile
docs/authors.rst
docs/contributing.rst
docs/history.rst
docs/index.rst
docs/installation.rst
docs/make.bat
docs/readme.rst
docs/usage.rst