Metadata-Version: 1.1
Name: BioCompass
Version: 0.9.2
Summary: Python package for gene clustering
Home-page: https://github.com/NP-Omix/BioCompass
Author: Tiago Leão, Gui Castelão
Author-email: tferreir@ucsd.edu, guilherme@castelao.net
License: BSD license
Keywords: BioCompass
Platform: UNKNOWN
Classifier: Development Status :: 3 - Alpha
Classifier: Intended Audience :: Developers
Classifier: License :: OSI Approved :: BSD License
Classifier: Natural Language :: English
Classifier: Programming Language :: Python :: 2
Classifier: Programming Language :: Python :: 2.7
